sdh/crossgrid/__init__.py
sdh/crossgrid/column.py
sdh/crossgrid/report.py
sdh/crossgrid/row.py
sdh/crossgrid/types.py
sdh.cross_grid-1.1.0.dist-info/LICENSE
sdh.cross_grid-1.1.0.dist-info/METADATA
sdh.cross_grid-1.1.0.dist-info/WHEEL
sdh.cross_grid-1.1.0.dist-info/top_level.txt
sdh.cross_grid-1.1.0.dist-info/RECORD
