Metadata-Version: 2.1
Name: sdh.cross-grid
Version: 1.1.0
Summary: Cross-grid report engine
Author-email: Viacheslav Vic Bukhantsov <vic.bukhantsov@gmail.com>
Maintainer-email: Viacheslav Vic Bukhantsov <vic.bukhantsov@gmail.com>
License: Copyright (c) 2024, SDH-IT GmbH
Project-URL: Repository, https://github.com/sdh-global/sdh-crossgrid
Classifier: Development Status :: 5 - Production/Stable
Classifier: Intended Audience :: Developers
Classifier: License :: OSI Approved :: BSD License
Classifier: Operating System :: OS Independent
Classifier: Programming Language :: Python
Classifier: Programming Language :: Python :: 3
Classifier: Programming Language :: Python :: 3.8
Classifier: Programming Language :: Python :: 3.9
Classifier: Topic :: Software Development :: Libraries :: Python Modules
Requires-Python: >=3.8
License-File: LICENSE
